momo/__init__.py
momo/__main__.py
momo/cli.py
tests/__init__.py
tests/test_01.py
momo_ma-0.1.1.dist-info/METADATA
momo_ma-0.1.1.dist-info/WHEEL
momo_ma-0.1.1.dist-info/entry_points.txt
momo_ma-0.1.1.dist-info/top_level.txt
momo_ma-0.1.1.dist-info/RECORD
