Metadata-Version: 2.1
Name: momo-ma
Version: 0.1.1
Summary: UNKNOWN
Home-page: UNKNOWN
Author: Weicai
Author-email: liuweicai90s@126.com
License: UNKNOWN
Platform: UNKNOWN
Requires-Dist: click
Requires-Dist: colorama
Requires-Dist: selenium
Requires-Dist: pyfiglet
